README.md
setup.py
CurrencyExchange.egg-info/PKG-INFO
CurrencyExchange.egg-info/SOURCES.txt
CurrencyExchange.egg-info/dependency_links.txt
CurrencyExchange.egg-info/requires.txt
CurrencyExchange.egg-info/top_level.txt
src/CurrencyExchange.py
src/__init__.py