Metadata-Version: 2.1
Name: CurrencyExchange
Version: 1.0.3
Summary: A Python package that converts currencies and validates currency codes.
Home-page: https://github.com/royshadmon/Currency-Exchange
Author: Roy Shadmon
Author-email: rshadmon@gmail.com
License: MIT
Platform: UNKNOWN
Classifier: Development Status :: 1 - Planning
Classifier: Intended Audience :: Science/Research
Classifier: License :: OSI Approved :: MIT License
Classifier: Operating System :: POSIX :: Linux
Classifier: Programming Language :: Python :: 3
Classifier: Programming Language :: Python :: 3.4
Classifier: Programming Language :: Python :: 3.5
